joacorapela_common/__init__.py
joacorapela_common/stats/__init__.py
joacorapela_common/stats/bayesianLinearRegression.py
joacorapela_common/utils/__init__.py
joacorapela_common/utils/geometry.py
joacorapela_common/utils/numerical_methods.py
joacorapela_common/utils/probability.py
joacorapela_common-1.0.6.dist-info/METADATA
joacorapela_common-1.0.6.dist-info/WHEEL
joacorapela_common-1.0.6.dist-info/top_level.txt
joacorapela_common-1.0.6.dist-info/RECORD
