Metadata-Version: 2.1
Name: joacorapela-common
Version: 1.0.6
Summary: Repository of common functionality for joacorapela's codebase
Home-page: https://github.com/joacorapela/joacorapela_common
Author: Joaquin Rapela
Author-email: joacorapela@gmail.com
License: MIT
Classifier: License :: OSI Approved :: MIT License
Classifier: Programming Language :: Python :: 3.7
Requires-Dist: numpy
Requires-Dist: scipy
